chatroom_syncer/__main__.py
chatroom_syncer/emoji.py
chatroom_syncer/plugins/__init__.py
chatroom_syncer/plugins/github_sink.py
chatroom_syncer/plugins/slack_sink.py
chatroom_syncer/room_syncer.py
chatroom_syncer/utils.py
chatroom_syncer-0.1.9.dist-info/WHEEL
chatroom_syncer-0.1.9.dist-info/METADATA
chatroom_syncer-0.1.9.dist-info/licenses/LICENSE
chatroom_syncer-0.1.9.dist-info/RECORD
