Metadata-Version: 2.1
Name: chatroom-syncer
Version: 0.1.9
Summary: Sync your IM group chat to Slack.
License: apache-2.0
Author-email: Wey Gu <weyl.gu@gmail.com>
Requires-Python: >=3.8
Requires-Dist: aiohttp>=3.8.3
Requires-Dist: python-dotenv>=0.21.0
Requires-Dist: pyyaml==6.0
Requires-Dist: quart==0.18.0
Requires-Dist: slack-sdk==3.19.5
Requires-Dist: wechaty-plugin-contrib>=0.0.19
Requires-Dist: wechaty==0.8.66
Project-URL: Homepage, https://github.com/wey-gu/chatroom-syncer
Project-URL: Repository, https://github.com/wey-gu/chatroom-syncer
